.gitignore
INSTALL.md
MANIFEST.in
README.md
setup.py
helloworld/__init__.py
helloworld/main.py
stblhnv_helloworld.egg-info/PKG-INFO
stblhnv_helloworld.egg-info/SOURCES.txt
stblhnv_helloworld.egg-info/dependency_links.txt
stblhnv_helloworld.egg-info/requires.txt
stblhnv_helloworld.egg-info/top_level.txt