Metadata-Version: 1.0
Name: stblhnv-helloworld
Version: 1.0
Summary: UNKNOWN
Home-page: UNKNOWN
Author: Stanislav Balahonov
Author-email: stanislav.balahonov@simbirsoft.com
License: UNKNOWN
Platform: UNKNOWN
